mdk/__init__.py
mdk/__main__.py
mdk/backup.py
mdk/ci.py
mdk/command.py
mdk/config-dist.json
mdk/config.py
mdk/container.py
mdk/css.py
mdk/db.py
mdk/exceptions.py
mdk/fetch.py
mdk/git.py
mdk/jira.py
mdk/js.py
mdk/moodle.py
mdk/phpunit.py
mdk/plugins.py
mdk/scripts.py
mdk/tools.py
mdk/version.py
mdk/workplace.py
mdk/commands/__init__.py
mdk/commands/alias.py
mdk/commands/backport.py
mdk/commands/backup.py
mdk/commands/behat.py
mdk/commands/config.py
mdk/commands/create.py
mdk/commands/cron.py
mdk/commands/css.py
mdk/commands/doctor.py
mdk/commands/fix.py
mdk/commands/info.py
mdk/commands/init.py
mdk/commands/install.py
mdk/commands/js.py
mdk/commands/php.py
mdk/commands/phpunit.py
mdk/commands/plugin.py
mdk/commands/precheck.py
mdk/commands/pull.py
mdk/commands/purge.py
mdk/commands/push.py
mdk/commands/rebase.py
mdk/commands/remove.py
mdk/commands/run.py
mdk/commands/tracker.py
mdk/commands/uninstall.py
mdk/commands/update.py
mdk/commands/upgrade.py
mdk/scripts/README.rst
mdk/scripts/dev.php
mdk/scripts/enrol.php
mdk/scripts/external_functions.php
mdk/scripts/jsconfig.php
mdk/scripts/less.sh
mdk/scripts/makecourse.sh
mdk/scripts/mincron.php
mdk/scripts/mindev.php
mdk/scripts/setup.sh
mdk/scripts/setupsecurity.sh
mdk/scripts/tokens.php
mdk/scripts/undev.php
mdk/scripts/users.php
mdk/scripts/version.php
mdk/scripts/webservices.php
moodle_sdk-2.1.4.dist-info/licenses/LICENSE.txt
moodle_sdk-2.1.4.dist-info/METADATA
moodle_sdk-2.1.4.dist-info/WHEEL
moodle_sdk-2.1.4.dist-info/entry_points.txt
moodle_sdk-2.1.4.dist-info/top_level.txt
moodle_sdk-2.1.4.dist-info/RECORD
