Metadata-Version: 2.4
Name: moodle-sdk
Version: 2.1.4
Summary: Moodle Development Kit
Home-page: https://github.com/FMCorz/mdk
Author: Frédéric Massart
Author-email: fred@fmcorz.net
License: MIT
Keywords: mdk moodle moodle-sdk
Classifier: Development Status :: 6 - Mature
Classifier: Intended Audience :: Developers
Classifier: License :: OSI Approved :: MIT License
Classifier: Natural Language :: English
Classifier: Operating System :: MacOS
Classifier: Operating System :: POSIX :: Linux
Classifier: Programming Language :: Python :: 3.6
Classifier: Topic :: Education
Classifier: Topic :: Software Development
Classifier: Topic :: Utilities
License-File: LICENSE.txt
Requires-Dist: keyring>=3.5
Requires-Dist: jenkinsapi>=0.3.2
Requires-Dist: mysqlclient>=1.4.5
Requires-Dist: psycopg2>=2.4.5
Requires-Dist: requests>2.3.0
Requires-Dist: watchdog>=0.8.0
Requires-Dist: pyodbc>=4.0.21
Dynamic: author
Dynamic: author-email
Dynamic: classifier
Dynamic: description
Dynamic: home-page
Dynamic: keywords
Dynamic: license
Dynamic: license-file
Dynamic: requires-dist
Dynamic: summary
